<annotation verified="yes">
	<folder>Ball1</folder>
	<filename>ball.images277.jpg</filename>
	<path>/home/khalisha/Ball1/ball.images277.jpg</path>
	<source>
		<database>Unknown</database>
	</source>
	<size>
		<width>640</width>
		<height>480</height>
		<depth>3</depth>
	</size>
	<segmented>0</segmented>
	<object>
		<name>ball</name>
		<pose>Unspecified</pose>
		<truncated>0</truncated>
		<difficult>0</difficult>
		<bndbox>
			<xmin>359</xmin>
			<ymin>158</ymin>
			<xmax>582</xmax>
			<ymax>372</ymax>
		</bndbox>
	</object>
</annotation>
